{
  "project_info": {
    "project_number": "76765376403",
    "firebase_url": "https://my-application-b159e.firebaseio.com",
    "project_id": "my-application-b159e",
    "storage_bucket": "my-application-b159e.appspot.com"
  },
  "client": [
    {
      "client_info": {
        "mobilesdk_app_id": "1:76765376403:android:369385f7802ea000f8c266",
        "android_client_info": {
          "package_name": "com.example.myapplication"
        }
      },
      "oauth_client": [
        {
          "client_id": "76765376403-45048qntmpbbp8k79l80c9nhb11opc63.apps.googleusercontent.com",
          "client_type": 1,
          "android_info": {
            "package_name": "com.example.myapplication",
            "certificate_hash": "a76e6ddf3f4147de19ab0ed9e2f7a257937c0b48"
          }
        },
        {
          "client_id": "76765376403-s322oktpnsmoengnn21pm71ijkj0kp17.apps.googleusercontent.com",
          "client_type": 3
        }
      ],
      "api_key": [
        {
          "current_key": "AIzaSyDMY0Mx6MEP07seT0PS1KHaTgYsyCJ-Oiw"
        }
      ],
      "services": {
        "appinvite_service": {
          "other_platform_oauth_client": [
            {
              "client_id": "76765376403-s322oktpnsmoengnn21pm71ijkj0kp17.apps.googleusercontent.com",
              "client_type": 3
            }
          ]
        }
      }
    }
  ],
  "configuration_version": "1"
}